orchd_ext/__init__.py
orchd_ext/reactions/__init__.py
orchd_ext/reactions/core.py
orchd_ext/sensors/__init__.py
orchd_ext/sinks/__init__.py
orchd_ext-0.1a3.dist-info/METADATA
orchd_ext-0.1a3.dist-info/WHEEL
orchd_ext-0.1a3.dist-info/top_level.txt
orchd_ext-0.1a3.dist-info/RECORD
