Metadata-Version: 2.1
Name: orchd-ext
Version: 0.1a3
Summary: Official orchd Extensions
Home-page: UNKNOWN
License: MIT
Platform: UNKNOWN
Classifier: Programming Language :: Python :: 3.8
Classifier: Programming Language :: Python :: 3.9
Classifier: Programming Language :: Python :: 3.10
Requires-Dist: orchd-sdk
Requires-Dist: pydantic
Requires-Dist: reactivex
Provides-Extra: rest
Requires-Dist: docutils (>=0.3) ; extra == 'rest'
Requires-Dist: pack (==1.1,==1.3) ; extra == 'rest'
